django_dump_die/__init__.py
django_dump_die/constants.py
django_dump_die/middleware.py
django_dump_die/test_urls.py
django_dump_die/urls.py
django_dump_die/utils.py
django_dump_die/static/django_dump_die/css/_toolbar_properties.css
django_dump_die/static/django_dump_die/css/dd.css
django_dump_die/static/django_dump_die/js/dd.js
django_dump_die/templates/django_dump_die/dd.html
django_dump_die/templates/django_dump_die/index.html
django_dump_die/templates/django_dump_die/sample.html
django_dump_die/templates/django_dump_die/test_index.html
django_dump_die/templates/django_dump_die/util_toolbar.html
django_dump_die/templates/django_dump_die/head_partials/_css_partial.html
django_dump_die/templates/django_dump_die/head_partials/_js_partial.html
django_dump_die/templates/django_dump_die/output_types/complex_type.html
django_dump_die/templates/django_dump_die/output_types/simple_type.html
django_dump_die/templates/django_dump_die/output_types/skipped_object.html
django_dump_die/templates/django_dump_die/partials/_attributes.html
django_dump_die/templates/django_dump_die/partials/_custom_color_theme.html
django_dump_die/templates/django_dump_die/partials/_dump.html
django_dump_die/templates/django_dump_die/partials/_dump_object.html
django_dump_die/templates/django_dump_die/partials/_dump_objects.html
django_dump_die/templates/django_dump_die/partials/_functions.html
django_dump_die/templatetags/__init__.py
django_dump_die/templatetags/dump_die.py
django_dump_die/views/__init__.py
django_dump_die/views/dd_view.py
django_dump_die/views/example_helpers.py
django_dump_die/views/example_views.py
django_dump_die/views/test_views.py
docs/source/conf.py
tests/__init__.py
tests/settings.py
tests/urls.py
tests/views.py
tests/test_views/__init__.py
tests/test_views/test_complex_type.py
tests/test_views/test_function_type.py
tests/test_views/test_intermediate_type.py
tests/test_views/test_request_response_cycle_type.py
tests/test_views/test_simple_type.py
django_dump_die-0.1.7.dist-info/LICENSE
django_dump_die-0.1.7.dist-info/METADATA
django_dump_die-0.1.7.dist-info/WHEEL
django_dump_die-0.1.7.dist-info/top_level.txt
django_dump_die-0.1.7.dist-info/RECORD
