Metadata-Version: 2.1
Name: django-dump-die
Version: 0.1.7
Summary: A Django app to add Laravel/Symfony-like dump and die functionality.
Home-page: https://github.com/DJBarnes/django-dump-die
Author: David Barnes, Brandon Rodriguez
Author-email: David Barnes <barnesdavidj@gmail.com>, Brandon Rodriguez <brodriguez8774@gmail.com>
Maintainer-email: David Barnes <barnesdavidj@gmail.com>, Brandon Rodriguez <brodriguez8774@gmail.com>
License: MIT License
Project-URL: Homepage, https://github.com/djbarnes/django-dump-die
Keywords: debug,dd,die,django,dump,inspect,tool
Classifier: Environment :: Web Environment
Classifier: Framework :: Django
Classifier: Framework :: Django :: 3
Classifier: Framework :: Django :: 3.2
Classifier: Framework :: Django :: 4
Classifier: Framework :: Django :: 4.0
Classifier: Framework :: Django :: 4.1
Classifier: Framework :: Django :: 4.2
Classifier: Intended Audience :: Developers
Classifier: License :: OSI Approved :: MIT License
Classifier: Operating System :: OS Independent
Classifier: Programming Language :: Python
Classifier: Programming Language :: Python :: 3
Classifier: Programming Language :: Python :: 3 :: Only
Classifier: Programming Language :: Python :: 3.8
Classifier: Programming Language :: Python :: 3.9
Classifier: Programming Language :: Python :: 3.10
Classifier: Programming Language :: Python :: 3.11
Classifier: Topic :: Internet :: WWW/HTTP
Classifier: Topic :: Internet :: WWW/HTTP :: Dynamic Content
Requires-Python: >=3.8
License-File: LICENSE
Requires-Dist: django>=3.2.0
Provides-Extra: dev
Requires-Dist: black; extra == "dev"
Requires-Dist: coverage; extra == "dev"
Requires-Dist: pylint; extra == "dev"
Requires-Dist: pylint-django; extra == "dev"
Provides-Extra: doc
Requires-Dist: doc8; extra == "doc"
Requires-Dist: esbonio; extra == "doc"
Requires-Dist: pip-tools; extra == "doc"
Requires-Dist: rstcheck; extra == "doc"
Requires-Dist: sphinx; extra == "doc"
Requires-Dist: sphinx-autobuild; extra == "doc"
Requires-Dist: sphinx-rtd-theme; extra == "doc"
